modrinth/__init__.py
modrinth-0.1.5.dist-info/METADATA
modrinth-0.1.5.dist-info/WHEEL
modrinth-0.1.5.dist-info/top_level.txt
modrinth-0.1.5.dist-info/RECORD
